nox_poetry/__init__.py
nox_poetry/poetry.py
nox_poetry/py.typed
nox_poetry/sessions.py
nox_poetry/sessions.pyi
nox_poetry-1.2.0.dist-info/LICENSE
nox_poetry-1.2.0.dist-info/METADATA
nox_poetry-1.2.0.dist-info/WHEEL
nox_poetry-1.2.0.dist-info/RECORD
