Metadata-Version: 2.3
Name: nox-poetry
Version: 1.2.0
Summary: nox-poetry
License: MIT
Author: Claudio Jolowicz
Author-email: mail@claudiojolowicz.com
Requires-Python: >=3.9
Classifier: Development Status :: 5 - Production/Stable
Classifier: License :: OSI Approved :: MIT License
Classifier: Programming Language :: Python :: 3
Classifier: Programming Language :: Python :: 3.9
Classifier: Programming Language :: Python :: 3.10
Classifier: Programming Language :: Python :: 3.11
Classifier: Programming Language :: Python :: 3.12
Classifier: Programming Language :: Python :: 3.13
Requires-Dist: build (>=1.2)
Requires-Dist: nox (>=2020.8.22)
Requires-Dist: packaging (>=20.9)
Requires-Dist: tomlkit (>=0.7)
Project-URL: Changelog, https://github.com/cjolowicz/nox-poetry/releases
Project-URL: Documentation, https://nox-poetry.readthedocs.io
Project-URL: Homepage, https://github.com/cjolowicz/nox-poetry
Project-URL: Repository, https://github.com/cjolowicz/nox-poetry
